steam_api/__init__.py
steam_api/app.py
steam_api/auth.py
steam_api/error.py
steam_api/news.py
steam_api/user.py
steam_api/user_stats.py
steam_api/api/__init__.py
steam_api/api/app.py
steam_api/api/const.py
steam_api/api/language_code.py
steam_api/api/news.py
steam_api/api/req.py
steam_api/api/user.py
steam_api/api/user_stats.py
steam_api/api/validator.py
steam_api-0.0.12.dist-info/DESCRIPTION.rst
steam_api-0.0.12.dist-info/METADATA
steam_api-0.0.12.dist-info/RECORD
steam_api-0.0.12.dist-info/WHEEL
steam_api-0.0.12.dist-info/metadata.json
steam_api-0.0.12.dist-info/top_level.txt
