Metadata-Version: 2.0
Name: steam-api
Version: 0.0.12
Summary: simple python wrapper for Steam web API
Home-page: UNKNOWN
Author: edmundluk
Author-email: edmundluk3@gmail.com
License: MIT
Keywords: steam api
Platform: UNKNOWN
Classifier: Development Status :: 3 - Alpha
Classifier: Intended Audience :: Developers
Classifier: Topic :: Software Development :: Build Tools
Classifier: License :: OSI Approved :: MIT License
Classifier: Programming Language :: Python :: 2
Classifier: Programming Language :: Python :: 2.6
Classifier: Programming Language :: Python :: 2.7
Classifier: Programming Language :: Python :: 3
Classifier: Programming Language :: Python :: 3.2
Classifier: Programming Language :: Python :: 3.3
Classifier: Programming Language :: Python :: 3.4
Requires-Dist: certifi (==2017.7.27.1)
Requires-Dist: chardet (==3.0.4)
Requires-Dist: future (==0.16.0)
Requires-Dist: idna (==2.6)
Requires-Dist: pluggy (==0.5.2)
Requires-Dist: py (==1.4.34)
Requires-Dist: requests (==2.18.4)
Requires-Dist: six (==1.11.0)
Requires-Dist: urllib3 (==1.22)
